<?xml version="1.0" ?>
<!DOCTYPE bulletml SYSTEM "bulletml.dtd">
<bulletml>
  <action label="top">
    <fire>
      <bullet>
        <direction type="aim">0</direction>
        <speed>8</speed>
        <sprite>4</sprite>
        <action>
          <repeat>
            <times>0</times>
            <action>
              <changeDirection>
                <direction type="aim">0</direction>
                <term>0</term>
              </changeDirection>
              <wait>1</wait>
            </action>
          </repeat>
        </action>
      </bullet>
    </fire>
  </action>
</bulletml>